Metadata-Version: 2.1
Name: example-pkg-dejac001
Version: 0.0.1
Summary: Distillation for Chemical Engineers
Home-page: https://github.com/dejac001/distillation
Author: Robert F. De Jaco
Author-email: dejac001@umn.edu
License: UNKNOWN
Platform: UNKNOWN
Classifier: Programming Language :: Python :: 3
Classifier: License :: OSI Approved :: GNU Lesser General Public License v3 (LGPLv3)
Classifier: Operating System :: OS Independent
Requires-Python: >=3.6
